{
"app_name" : "รถเข็นรองเท้า",
"action_settings" : "การตั้งค่า",
"arrival" : "การมาถึง",
"filter" : "ตัวกรอง",
"location" : "ที่ตั้ง",
"sort_by" : "เรียงตาม",
"cancel" : "ยกเลิก",
"apply" : "นำมาใช้",
"price" : "ราคา",
"items_listed" : "รายการที่ระบุไว้",
"sort" : "เรียงลำดับ",
"buy_now" : "ซื้อเลย",
"checkout" : "เช็คเอาท์",
"saved_payment_method" : "วิธีการชำระเงินที่บันทึกไว้",
"pay_now" : "จ่ายตอนนี้",
"other_payment_options" : "ตัวเลือกการชำระเงินอื่น ๆ",
"wallets" : "กระเป๋าสตางค์",
"credit_card" : "บัตรเครดิต",
"safe_and_secure_payments" : "การชำระเงินที่ปลอดภัยและมั่นคง",
"card_number" : "หมายเลขบัตร",
"enter_mobile_no" : "ใส่เบอร์มือถือ",
"other_options" : "ตัวเลือกอื่น",
"success" : "สำเร็จ",
"fail" : "ล้มเหลว",
"this_field_is_required" : "ต้องกรอกช่องนี้.",
"invalid_mobile_number_error" : "โปรดป้อนหมายเลขอินเดียที่ถูกต้อง",
"otp_has_been_sent" : "ส่ง OTP ไปที่ .ของคุณแล้ว",
"error_no_internet_connectivity" : "ไม่มีการเชื่อมต่ออินเทอร์เน็ต. โปรดตรวจสอบการตั้งค่าอินเทอร์เน็ตของคุณและลองอีกครั้ง",
"error_oops_something_went_wrong" : "อ๊ะ! มีบางอย่างผิดพลาด โปรดลองอีกครั้ง…",
"error_verify_otp" : "กรุณาตรวจสอบรหัส OTP ที่ได้รับ",
"select_one_payment_method" : "เลือกวิธีการชำระเงินอย่างน้อยหนึ่งวิธี",
"fill_all_card_details" : "กรอกรายละเอียดบัตรทั้งหมด",
"continue_shopping" : "ช้อปปิ้งต่อ",
"phone_no" : "หมายเลขโทรศัพท์:",
"verify" : "ตรวจสอบ",
"merchant_order_ref" : "อ้างอิงคำสั่งซื้อของผู้ค้า:",
"channel_order_ref" : "ช่องทางการสั่งซื้ออ้างอิง:",
"status" : "สถานะ",
"payment_successful" : "การชำระเงินสำเร็จ",
"payment_failed" : "การชำระเงินล้มเหลว",
"card_holder_name" : "ชื่อผู้ถือบัตร",
"month" : "เดือน",
"year" : "ปี",
"no_data_available" : "ไม่มีข้อมูลที่สามารถใช้ได้",
"no_saved_cards" : "ไม่มีการ์ดที่บันทึกไว้",
"get_otp" : "รับ Otp",
"web_checkout" : "เว็บชำระเงิน",
"custom_checkout" : "ชำระเงินแบบกำหนดเอง",
"please_enter_valid_mobile_no" : "โปรดป้อนหมายเลขโทรศัพท์มือถือที่ถูกต้อง",
"please_enter_valid_otp" : "โปรดป้อน OTP . ที่ถูกต้อง",
"payout" : "การจ่ายเงิน",
"payout_status" : "สถานะการจ่ายเงิน",
"payment_type" : "ประเภทการชำระเงิน",
"dismiss" : "ยกเลิก",
"error_no_app_found" : "ไม่พบแอป",
"no_intent_client_found" : "ไม่พบแอปที่ต้องการในเครื่องนี้",
"tap_to_retry" : "แตะเพื่อลองใหม่",
"something_went_wrong" : "อ๊ะ.. มีบางอย่างผิดพลาด!!",
"no_internet_connection" : "ไม่มีการเชื่อมต่ออินเทอร์เน็ต",
"home" : "บ้าน",
"profile" : "ประวัติโดยย่อ",
"my_cart" : "รถเข็นของฉัน",
"saved_cards" : "การ์ดที่บันทึกไว้",
"ATM_card" : "บัตรเอทีเอ็ม",
"total" : "รวม",
"exp_date" : "วันหมดอายุ",
"cvv" : "CVV",
"alert_option" : "โปรดเลือกหนึ่งในวิธี UI ด้านล่างเพื่อดำเนินการต่อ",
"Change_Language_Msg" : "กรุณาเลือกภาษาของคุณ จำเป็นต้องรีสตาร์ทเพื่อนำไปใช้ในการเปลี่ยนแปลง",
"transaction_failed" : "การทำธุรกรรมล้มเหลว",
"order":"คำสั่ง",
"delivery": "จัดส่ง",
"amount_toPaid": "Amount to be paid",
"amount_paid": "จำนวนเงินที่จ่าย"
}